gnssl76l.py
setup.py
micropython_gnssl76l.egg-info/PKG-INFO
micropython_gnssl76l.egg-info/SOURCES.txt
micropython_gnssl76l.egg-info/dependency_links.txt
micropython_gnssl76l.egg-info/top_level.txt