Metadata-Version: 1.1
Name: micropython-gnssl76l
Version: 0.1.0
Summary: MicroPython I2C driver for the Quectel GNSS L76-L (GPS) receiver
Home-page: https://github.com/tuupola/micropython-gnssl76l
Author: Mika Tuupola
Author-email: tuupola@appelsiini.net
License: MIT
Keywords: gps glonass galileo qzss micropython i2c
Platform: UNKNOWN
Classifier: Development Status :: 2 - Pre-Alpha
Classifier: Programming Language :: Python :: Implementation :: MicroPython
Classifier: License :: OSI Approved :: MIT License
